zepben/evolve/__init__.py
zepben/evolve/exceptions.py
zepben/evolve/types.py
zepben/evolve/util.py
zepben/evolve/database/__init__.py
zepben/evolve/database/sqlite/__init__.py
zepben/evolve/database/sqlite/database_reader.py
zepben/evolve/database/sqlite/database_writer.py
zepben/evolve/database/sqlite/readers/__init__.py
zepben/evolve/database/sqlite/readers/base_cim_reader.py
zepben/evolve/database/sqlite/readers/base_service_reader.py
zepben/evolve/database/sqlite/readers/customer_cim_reader.py
zepben/evolve/database/sqlite/readers/customer_service_reader.py
zepben/evolve/database/sqlite/readers/diagram_cim_reader.py
zepben/evolve/database/sqlite/readers/diagram_service_reader.py
zepben/evolve/database/sqlite/readers/metadata_collection_reader.py
zepben/evolve/database/sqlite/readers/metadata_entry_reader.py
zepben/evolve/database/sqlite/readers/network_cim_reader.py
zepben/evolve/database/sqlite/readers/network_service_reader.py
zepben/evolve/database/sqlite/readers/result_set.py
zepben/evolve/database/sqlite/tables/__init__.py
zepben/evolve/database/sqlite/tables/column.py
zepben/evolve/database/sqlite/tables/database_tables.py
zepben/evolve/database/sqlite/tables/exceptions.py
zepben/evolve/database/sqlite/tables/metadata_tables.py
zepben/evolve/database/sqlite/tables/sqlite_table.py
zepben/evolve/database/sqlite/tables/associations/__init__.py
zepben/evolve/database/sqlite/tables/associations/assetorganisationroles_association_tables.py
zepben/evolve/database/sqlite/tables/associations/circuit_association_tables.py
zepben/evolve/database/sqlite/tables/associations/customeragreements_association_tables.py
zepben/evolve/database/sqlite/tables/associations/equipment_association_tables.py
zepben/evolve/database/sqlite/tables/associations/loop_association_tables.py
zepben/evolve/database/sqlite/tables/associations/pricingstructure_association_tables.py
zepben/evolve/database/sqlite/tables/associations/usagepoints_association_tables.py
zepben_evolve_test_ci_central-0.34.0.dist-info/licenses/LICENSE
zepben_evolve_test_ci_central-0.34.0.dist-info/METADATA
zepben_evolve_test_ci_central-0.34.0.dist-info/WHEEL
zepben_evolve_test_ci_central-0.34.0.dist-info/top_level.txt
zepben_evolve_test_ci_central-0.34.0.dist-info/RECORD
